puya/__init__.py
puya/__main__.py
puya/algo_constants.py
puya/arc32.py
puya/arc56.py
puya/arc56_models.py
puya/artifact_metadata.py
puya/artifact_sorter.py
puya/avm.py
puya/compilation_artifacts.py
puya/compile.py
puya/context.py
puya/errors.py
puya/log.py
puya/main.py
puya/options.py
puya/parse.py
puya/program_refs.py
puya/py.typed
puya/service.py
puya/utils.py
puya/awst/__init__.py
puya/awst/awst_traverser.py
puya/awst/function_traverser.py
puya/awst/nodes.py
puya/awst/serialize.py
puya/awst/to_code_visitor.py
puya/awst/txn_fields.py
puya/awst/visitors.py
puya/awst/wtypes.py
puya/awst/validation/__init__.py
puya/awst/validation/abi_method_name.py
puya/awst/validation/base_invoker.py
puya/awst/validation/immutable.py
puya/awst/validation/inner_transactions.py
puya/awst/validation/labels.py
puya/awst/validation/main.py
puya/awst/validation/storage.py
puya/ir/__init__.py
puya/ir/_arc4_default_args.py
puya/ir/_contract_metadata.py
puya/ir/_puya_lib.awst.json
puya/ir/_puya_lib.py
puya/ir/_utils.py
puya/ir/arc4_router.py
puya/ir/arc4_types.py
puya/ir/avm_ops.py
puya/ir/avm_ops_models.py
puya/ir/context.py
puya/ir/encodings.py
puya/ir/main.py
puya/ir/models.py
puya/ir/mutating_register_context.py
puya/ir/op_utils.py
puya/ir/register_context.py
puya/ir/register_read_collector.py
puya/ir/ssa.py
puya/ir/to_text_visitor.py
puya/ir/types_.py
puya/ir/utils.py
puya/ir/visitor.py
puya/ir/visitor_mem_replacer.py
puya/ir/visitor_mutator.py
puya/ir/vla.py
puya/ir/builder/__init__.py
puya/ir/builder/_utils.py
puya/ir/builder/assignment.py
puya/ir/builder/blocks.py
puya/ir/builder/bytes.py
puya/ir/builder/callsub.py
puya/ir/builder/dynamic_array.py
puya/ir/builder/encoding_validation.py
puya/ir/builder/flow_control.py
puya/ir/builder/iteration.py
puya/ir/builder/itxn.py
puya/ir/builder/main.py
puya/ir/builder/mem.py
puya/ir/builder/sequence.py
puya/ir/builder/storage.py
puya/ir/builder/aggregates/__init__.py
puya/ir/builder/aggregates/arc4_codecs.py
puyapy-5.6.0.dist-info/METADATA
puyapy-5.6.0.dist-info/WHEEL
puyapy-5.6.0.dist-info/entry_points.txt
puyapy-5.6.0.dist-info/licenses/COPYING
puyapy-5.6.0.dist-info/licenses/LICENSE
puyapy-5.6.0.dist-info/RECORD
