Metadata-Version: 2.4
Name: puyapy
Version: 5.6.0
Summary: An optimising compiler for Algorand Python
Author-email: Algorand Foundation <contact@algorand.foundation>
License-Expression: AGPL-3.0-or-later
License-File: COPYING
License-File: LICENSE
Classifier: Development Status :: 5 - Production/Stable
Classifier: Intended Audience :: Developers
Classifier: Topic :: Software Development :: Compilers
Requires-Python: <4,>=3.12.0
Requires-Dist: attrs<26,>=25.3.0
Requires-Dist: cattrs<26,>=25
Requires-Dist: colorama<0.5,>=0.4.6; sys_platform == 'win32'
Requires-Dist: cyclopts>=3.23.1
Requires-Dist: docstring-parser>=0.14.1
Requires-Dist: immutabledict<5,>=4.2.0
Requires-Dist: mypy==1.19.1
Requires-Dist: networkx<4,>=3.6
Requires-Dist: packaging~=24.0
Requires-Dist: pycryptodomex<4,>=3.6.0
Requires-Dist: pygls>=2.0.0a2
Requires-Dist: structlog<26,>=25.2.0
Requires-Dist: typing-extensions<5,>=4.11.0
